{
  "title": "FrontmostIfVscode",
  "rules": [
    {
      "description": "LeftCommand + N_HeadRowCursol(vscode)",
      "manipulators": [
        {
          "type": "basic",
          "from": {
            "key_code": "n",
            "modifiers": {
              "mandatory": [
                "left_control"
              ]
            }
          },
          "to": [
            {
              "key_code": "up_arrow",
              "modifiers": [
                "right_gui"
              ]
            }
          ],
          "conditions": [
            {
              "type": "frontmost_application_if",
              "bundle_identifiers": [
                "^com.microsoft.VSCode$"
              ]
            }
          ]
        }
      ]
    },
    {
      "description": "LeftCommand + M_EndRowCursol(vscode)",
      "manipulators": [
        {
          "type": "basic",
          "from": {
            "key_code": "m",
            "modifiers": {
              "mandatory": [
                "left_control"
              ]
            }
          },
          "to": [
            {
              "key_code": "down_arrow",
              "modifiers": [
                "right_gui"
              ]
            }
          ],
          "conditions": [
            {
              "type": "frontmost_application_if",
              "bundle_identifiers": [
                "^com.microsoft.VSCode$"
              ]
            }
          ]
        }
      ]
    },
    {
      "description": "LeftCommand + CloseBracket_unindent(vscode)",
      "manipulators": [
        {
          "type": "basic",
          "from": {
            "key_code": "close_bracket",
            "modifiers": {
              "mandatory": [
                "left_control"
              ]
            }
          },
          "to": [
            {
              "key_code": "1",
              "modifiers": [
                "left_control"
              ]
            }
          ],
          "conditions": [
            {
              "type": "frontmost_application_if",
              "bundle_identifiers": [
                "^com.microsoft.VSCode$"
              ]
            }
          ]
        }
      ]
    },
    {
      "description": "RightCommand + Slash_SelectAllSameWord(vscode)",
      "manipulators": [
        {
          "type": "basic",
          "from": {
            "key_code": "slash",
            "modifiers": {
              "mandatory": [
                "right_gui"
              ]
            }
          },
          "to": [
            {
              "key_code": "2",
              "modifiers": [
                "right_control"
              ]
            }
          ],
          "conditions": [
            {
              "type": "frontmost_application_if",
              "bundle_identifiers": [
                "^com.microsoft.VSCode$"
              ]
            }
          ]
        }
      ]
    },
    {
      "description": "LeftAlt + B_DebugStart (vscode)",
      "manipulators": [
        {
          "type": "basic",
          "from": {
            "key_code": "b",
            "modifiers": {
              "mandatory": [
                "left_alt"
              ]
            }
          },
          "to": [
            {
              "key_code": "b",
              "modifiers": [
                "right_alt"
              ]
            }
          ],
          "conditions": [
            {
              "type": "frontmost_application_if",
              "bundle_identifiers": [
                "^com.microsoft.VSCode$"
              ]
            }
          ]
        }
      ]
    },
    {
      "description": "LeftAlt + I_Terminal Focus (vscode)",
      "manipulators": [
        {
          "type": "basic",
          "from": {
            "key_code": "i",
            "modifiers": {
              "mandatory": [
                "left_alt"
              ]
            }
          },
          "to": [
            {
              "key_code": "4",
              "modifiers": [
                "left_control",
                "left_alt"
              ]
            }
          ],
          "conditions": [
            {
              "type": "frontmost_application_if",
              "bundle_identifiers": [
                "^com.microsoft.VSCode$"
              ]
            }
          ]
        }
      ]
    },
    {
      "description": "RightCommand + Comma_Terminal Panel Max Toggle (vscode)",
      "manipulators": [
        {
          "type": "basic",
          "from": {
            "key_code": "comma",
            "modifiers": {
              "mandatory": [
                "right_gui"
              ]
            }
          },
          "to": [
            {
              "key_code": "o",
              "modifiers": [
                "left_control",
                "left_alt"
              ]
            }
          ],
          "conditions": [
            {
              "type": "frontmost_application_if",
              "bundle_identifiers": [
                "^com.microsoft.VSCode$"
              ]
            }
          ]
        }
      ]
    },
    {
      "description": "LeftAlt + U_Terminal Clear (vscode)",
      "manipulators": [
        {
          "type": "basic",
          "from": {
            "key_code": "u",
            "modifiers": {
              "mandatory": [
                "left_alt"
              ]
            }
          },
          "to": [
            {
              "key_code": "2",
              "modifiers": [
                "right_control",
                "left_alt"
              ]
            }
          ],
          "conditions": [
            {
              "type": "frontmost_application_if",
              "bundle_identifiers": [
                "^com.microsoft.VSCode$"
              ]
            }
          ]
        }
      ]
    },
    {
      "description": "LeftAlt + N_prettifyコード整形 (vscode)",
      "manipulators": [
        {
          "type": "basic",
          "from": {
            "key_code": "n",
            "modifiers": {
              "mandatory": [
                "left_alt"
              ]
            }
          },
          "to": [
            {
              "key_code": "f",
              "modifiers": [
                "right_alt",
                "left_shift"
              ]
            }
          ],
          "conditions": [
            {
              "type": "frontmost_application_if",
              "bundle_identifiers": [
                "^com.microsoft.VSCode$"
              ]
            }
          ]
        }
      ]
    },
    {
      "description": "LeftCommand + 0(ゼロ)_2RowSplitEditerScreen(vscode)",
      "manipulators": [
        {
          "type": "basic",
          "from": {
            "key_code": "0",
            "modifiers": {
              "mandatory": [
                "left_control"
              ]
            }
          },
          "to": [
            {
              "key_code": "2",
              "modifiers": [
                "right_alt",
                "right_gui",
                "right_shift"
              ]
            }
          ]
        }
      ]
    }
  ]
}
